{
  "sections": {
    "main": {
      "type": "main-product",
      "blocks": {
        "quantity_selector": {
          "type": "quantity_selector",
          "settings": {
          }
        },
        "buy_buttons": {
          "type": "buy_buttons",
          "settings": {
            "show_dynamic_checkout": false
          }
        }
      },
      "block_order": [
        "quantity_selector",
        "buy_buttons"
      ],
      "settings": {
        "enable_sticky_info": true,
        "gallery_layout": "thumbnail_slider",
        "media_size": "medium",
        "mobile_thumbnails": "show",
        "hide_variants": false,
        "enable_video_looping": false,
        "padding_top": 36,
        "padding_bottom": 12
      }
    },
    "product_benefits": {
      "type": "image-with-textblock-7923216",
      "blocks":{
        "header": {
          "type": "header",
          "settings": {}
        },
        "image": {
          "type": "image",
          "settings": {}
        },
        "richtext_1": {
          "type": "richtext",
          "settings": {}
        },
        "richtext_2": {
          "type": "richtext",
          "settings": {}
        },
        "richtext_3": {
          "type": "richtext",
          "settings": {}
        }
      },
      "block_order":[
        "header",
        "image",
        "richtext_1",
        "richtext_2",
        "richtext_3"
      ],
      "settings": {}
    },
    "before_after":{
      "type":"image-slider-7923216",
      "blocks":{
        "header": {
          "type": "header",
          "settings": {}
        },
        "slider": {
          "type": "slider",
          "settings": {}
        },
        "image_1": {
          "type": "image",
          "settings": {}
        },
        "image_2": {
          "type": "image",
          "settings": {}
        },
        "image_3": {
          "type": "image",
          "settings": {}
        }
      },
      "block_order":[
        "header",
        "slider",
        "image_1",
        "image_2",
        "image_3"
      ],
      "settings": {}
    },
    "wishlist_reference": {
      "type": "main-product-wishlist",
      "settings": {
        "image_ratio": "square",
        "show_secondary_image": true,
        "show_vendor": true,
        "show_rating": false
      }
    },
    "wave": {
      "type": "wave",
      "settings": {
        "color_scheme": "accent-2",
        "bg_color_top": "#ffffff",
        "padding_top": 36
      }
    }
  },
  "order": [
    "main",
    "product_benefits",
    "before_after",
    "wishlist_reference",
    "wave"
  ]
}
